Metadata-Version: 1.1
Name: sniper-jinja
Version: 0.0.3
Summary: a jinja2 plugin for sniper
Home-page: https://github.com/lexdene/sniper-jinja
Author: Elephant Liu
Author-email: lexdene@gmail.com
License: GPLv3
Platform: any
Classifier: Development Status :: 3 - Alpha
Classifier: Environment :: Web Environment
Classifier: Intended Audience :: Developers
Classifier: License :: OSI Approved :: GNU General Public License v3 (GPLv3)
Classifier: Operating System :: OS Independent
Classifier: Programming Language :: Python
Classifier: Programming Language :: Python :: 3.6
Classifier: Topic :: Internet :: WWW/HTTP
